<annotation>
	<folder>JPEGImages</folder>
	<filename>37.jpg</filename>
	<path>H:\Python\DL\Yolov3\train\VOCdevkit\VOC2007\JPEGImages\37.jpg</path>
	<source>
		<database>Unknown</database>
	</source>
	<size>
		<width>6016</width>
		<height>4016</height>
		<depth>3</depth>
	</size>
	<segmented>0</segmented>
	<object>
		<name>red</name>
		<pose>Unspecified</pose>
		<truncated>0</truncated>
		<difficult>0</difficult>
		<bndbox>
			<xmin>3468</xmin>
			<ymin>1434</ymin>
			<xmax>3647</xmax>
			<ymax>1913</ymax>
		</bndbox>
	</object>
	<object>
		<name>green</name>
		<pose>Unspecified</pose>
		<truncated>0</truncated>
		<difficult>0</difficult>
		<bndbox>
			<xmin>3760</xmin>
			<ymin>1447</ymin>
			<xmax>3935</xmax>
			<ymax>1918</ymax>
		</bndbox>
	</object>
	<object>
		<name>red</name>
		<pose>Unspecified</pose>
		<truncated>0</truncated>
		<difficult>0</difficult>
		<bndbox>
			<xmin>4010</xmin>
			<ymin>1426</ymin>
			<xmax>4222</xmax>
			<ymax>1918</ymax>
		</bndbox>
	</object>
</annotation>
